source/__init__.py
source/banner.txt
source/json/__init__.py
source/json/headers.json
src/__init__.py
src/request_session.py
src/network/__init__.py
src/network/download.py
src/network/request_session.py
src/sink/__init__.py
src/sink/sink2excel.py
src/utils/__init__.py
src/utils/config.py
toolboxs-0.1.1.dist-info/LICENSE
toolboxs-0.1.1.dist-info/METADATA
toolboxs-0.1.1.dist-info/WHEEL
toolboxs-0.1.1.dist-info/top_level.txt
toolboxs-0.1.1.dist-info/RECORD
