Metadata-Version: 2.1
Name: toolboxs
Version: 0.1.1
Summary: A box-ah package for python
Home-page: https://gitee.com/bu_xiu/toolboxs.git
Author: MR.AH
Author-email: zhangzhonghui1001@gmail.com
License: Apache
Classifier: Programming Language :: Python :: 3
Classifier: License :: OSI Approved :: MIT License
Classifier: Operating System :: OS Independent
Requires-Python: >=3
License-File: LICENSE
Requires-Dist: requests==2.31.0
Requires-Dist: lxml==5.1.0
